flamekit/__init__.py
flamekit/callbacks.py
flamekit/devices.py
flamekit/lr_scheduler.py
flamekit/pbars.py
flamekit/plotting.py
flamekit/sampling.py
flamekit/trainer.py
flamekit/training.py
flamekit/utils.py
flamekit/var_scheduler.py
flamekit-0.2.3.dist-info/LICENSE
flamekit-0.2.3.dist-info/METADATA
flamekit-0.2.3.dist-info/WHEEL
flamekit-0.2.3.dist-info/top_level.txt
flamekit-0.2.3.dist-info/RECORD
