Metadata-Version: 2.1
Name: flamekit
Version: 0.2.3
Summary: Minimalistic toolkit for PyTorch
Home-page: https://github.com/pgmesa/flamekit
Author: Pablo García Mesa
Author-email: pgmesa.sm@gmail.com
Classifier: Programming Language :: Python :: 3.9
Classifier: License :: OSI Approved :: MIT License
Classifier: Operating System :: OS Independent
Requires-Python: >=3.9
License-File: LICENSE
Requires-Dist: tabulate (>=0.9.0)
Requires-Dist: tqdm (>=4.65.0)
Requires-Dist: matplotlib (>=3.7.0)
Requires-Dist: numpy
